altaipony/__init__.py
altaipony/altai.py
altaipony/customdetrend.py
altaipony/detrend.py
altaipony/fakeflares.py
altaipony/ffd.py
altaipony/flarelc.py
altaipony/injrecanalysis.py
altaipony/k2scmod.py
altaipony/lcio.py
altaipony/utils.py
altaipony/version.py
altaipony/wheatland.py
altaipony/examples/kplr010002792-2009259160929_llc.fits
altaipony/examples/kplr010002792-2010174085026_llc.fits
altaipony/examples/ktwo210994964-c04_lpd-targ.fits
altaipony/examples/ktwo211117077-c04_llc.fits
altaipony/examples/ktwo211983544-c18_lpd-targ.fits
altaipony/examples/pony010002792-2009259160929_llc.fits
altaipony/examples/pony010002792-2009259160929_llc_test_from_path_AltaiPony.fits
altaipony/examples/tess2018206045859-s0001-0000000358108509-0120-s_lc.fits
altaipony/static/KS_leq_35_values.csv
altaipony/tests/__init__.py
altaipony/tests/test_altai.py
altaipony/tests/test_customdetrend.py
altaipony/tests/test_fakeflares.py
altaipony/tests/test_ffd.py
altaipony/tests/test_flarelc.py
altaipony/tests/test_injecanalysis.py
altaipony/tests/test_lcio.py
altaipony/tests/test_utils.py
altaipony/tests/test_wheatland.py
altaipony/tests/testfiles/gj1243_injrec.csv
altaipony/tests/testfiles/injrec_TIC1539914_s9.csv
altaipony/tests/testfiles/pony_k2sc_k2_llc_800000000-c05_kepler_v2_lc.fits
altaipony/tests/testfiles/testflares.csv
altaipony-2.1.2.dist-info/LICENSE
altaipony-2.1.2.dist-info/METADATA
altaipony-2.1.2.dist-info/WHEEL
altaipony-2.1.2.dist-info/top_level.txt
altaipony-2.1.2.dist-info/RECORD
