Metadata-Version: 2.1
Name: altaipony
Version: 2.1.2
Summary: Flare science in Kepler and TESS light curves
Home-page: https://github.com/ekaterinailin/AltaiPony
Author: Ekaterina Ilin
Author-email: eilin@aip.de
Classifier: Programming Language :: Python :: 3
Classifier: License :: OSI Approved :: MIT License
License-File: LICENSE
Requires-Dist: numpy >=1.15.1
Requires-Dist: pybind11
Requires-Dist: lightkurve >=2.4
Requires-Dist: pandas >=2.0
Requires-Dist: george >=0.3
Requires-Dist: progressbar2 >=3.51.4
Requires-Dist: seaborn
Requires-Dist: astropy >=5
Requires-Dist: k2sc >=1.0.2
Requires-Dist: emcee
Requires-Dist: corner
Requires-Dist: scipy >1.5
